ensembleswarm/regressors.py
ensembleswarm/swarm.py
ensembleswarm-1.0a3.dist-info/METADATA
ensembleswarm-1.0a3.dist-info/WHEEL
ensembleswarm-1.0a3.dist-info/licenses/LICENSE
ensembleswarm-1.0a3.dist-info/RECORD
