Metadata-Version: 2.4
Name: ensembleswarm
Version: 1.0a3
Summary: Ensemble of ensembles regression utility
Project-URL: Homepage, https://github.com/gperdrizet/ensembleswarm
Project-URL: Issues, https://github.com/gperdrizet/ensembleswarm/issues
Author-email: George Perdrizet <george@perdrizet.org>
License-File: LICENSE
Requires-Python: >=3.10
Requires-Dist: catboost
Requires-Dist: h5py
Requires-Dist: lightgbm
Requires-Dist: numpy
Requires-Dist: pandas
Requires-Dist: scikit-learn
Requires-Dist: xgboost
